meta_threads_mcp/__init__.py
meta_threads_mcp/auth.py
meta_threads_mcp/server.py
meta_threads_mcp/prompts/__init__.py
meta_threads_mcp/prompts/content.py
meta_threads_mcp/tools/__init__.py
meta_threads_mcp/tools/insights.py
meta_threads_mcp/tools/posts.py
meta_threads_mcp/tools/replies.py
meta_threads_mcp/tools/users.py
meta_threads_mcp-0.1.0.dist-info/METADATA
meta_threads_mcp-0.1.0.dist-info/WHEEL
meta_threads_mcp-0.1.0.dist-info/entry_points.txt
meta_threads_mcp-0.1.0.dist-info/licenses/LICENSE
meta_threads_mcp-0.1.0.dist-info/RECORD
