Metadata-Version: 2.4
Name: meta-threads-mcp
Version: 0.1.0
Summary: Unofficial MCP server for Meta's Threads API
Project-URL: Homepage, https://github.com/MetaThreads/meta-threads-mcp
Project-URL: Repository, https://github.com/MetaThreads/meta-threads-mcp
Project-URL: Issues, https://github.com/MetaThreads/meta-threads-mcp/issues
Author: MetaThreads
License: MIT
License-File: LICENSE
Keywords: api,mcp,meta,model-context-protocol,social-media,threads
Classifier: Development Status :: 4 - Beta
Classifier: Intended Audience :: Developers
Classifier: License :: OSI Approved :: MIT License
Classifier: Programming Language :: Python :: 3
Classifier: Programming Language :: Python :: 3.13
Classifier: Topic :: Software Development :: Libraries :: Python Modules
Requires-Python: >=3.13
Requires-Dist: fastmcp>=2.0.0
Requires-Dist: meta-threads-sdk>=0.2.0
